setup.py
src/lti_connectors.egg-info/PKG-INFO
src/lti_connectors.egg-info/SOURCES.txt
src/lti_connectors.egg-info/dependency_links.txt
src/lti_connectors.egg-info/requires.txt
src/lti_connectors.egg-info/top_level.txt
src/ltischoolbus/__init__.py
src/ltischoolbus/lti_schoolbus_bridge.py
src/ltischoolbus/jsmin/__init__.py
src/ltischoolbus/jsmin/__main__.py
src/ltischoolbus/jsmin/test.py
src/ltischoolbus/test/__init__.py
src/ltischoolbus/test/delivery_rx_server.py