Metadata-Version: 1.0
Name: lti-connectors
Version: 0.0.2
Summary: Example OLI analysis via SchoolBus communication.
Home-page: git@github.com:paepcke/lti_connectors.git
Author: Andreas Paepcke
Author-email: paepcke@cs.stanford.edu
License: BSD
Keywords: OLI
Platform: UNKNOWN
